shap_enhanced/__init__.py
shap_enhanced/base_explainer.py
shap_enhanced/explainers/ABSHAP.py
shap_enhanced/explainers/AttnSHAP.py
shap_enhanced/explainers/BSHAP.py
shap_enhanced/explainers/CASHAP.py
shap_enhanced/explainers/CMSHAP.py
shap_enhanced/explainers/ECSHAP.py
shap_enhanced/explainers/ERSHAP.py
shap_enhanced/explainers/ESSHAP.py
shap_enhanced/explainers/LatentSHAP.py
shap_enhanced/explainers/MBSHAP.py
shap_enhanced/explainers/RLSHAP.py
shap_enhanced/explainers/SCSHAP.py
shap_enhanced/explainers/SPSHAP.py
shap_enhanced/explainers/SurroSHAP.py
shap_enhanced/explainers/TimeSHAP.py
shap_enhanced/explainers/__init__.py
shap_enhanced/explainers/hSHAP.py
shap_enhanced/tools/__init__.py
shap_enhanced/tools/comparison.py
shap_enhanced/tools/datasets.py
shap_enhanced/tools/evaluation.py
shap_enhanced/tools/predefined_models.py
shap_enhanced/tools/timer.py
shap_enhanced/tools/visulization.py
shap_enhanced-0.0.1a2.dist-info/licenses/LICENSE
shap_enhanced-0.0.1a2.dist-info/METADATA
shap_enhanced-0.0.1a2.dist-info/WHEEL
shap_enhanced-0.0.1a2.dist-info/top_level.txt
shap_enhanced-0.0.1a2.dist-info/RECORD
