Metadata-Version: 2.4
Name: shap-enhanced
Version: 0.0.1a2
Summary: SHAP-style explainability with enhanced methods for sequential and tabular models
Author-email: Niyang Bai <bainiyang@gmail.com>
License:                     GNU AFFERO GENERAL PUBLIC LICENSE
Requires-Python: >=3.10
License-File: LICENSE
Requires-Dist: numpy
Requires-Dist: scipy
Requires-Dist: torch
Requires-Dist: shap
Requires-Dist: matplotlib
Requires-Dist: pandas
Requires-Dist: scikit-learn
Dynamic: license-file
